nonebot_plugin_dice_helper/__init__.py
nonebot_plugin_dice_helper/config.py
nonebot_plugin_dice_helper/custom_dice.py
nonebot_plugin_dice_helper/roll.py
nonebot_plugin_dice_helper/storage.py
nonebot_plugin_dice_helper/utils.py
nonebot_plugin_dice_helper-0.1.2.dist-info/licenses/LICENSE
nonebot_plugin_dice_helper-0.1.2.dist-info/METADATA
nonebot_plugin_dice_helper-0.1.2.dist-info/WHEEL
nonebot_plugin_dice_helper-0.1.2.dist-info/top_level.txt
nonebot_plugin_dice_helper-0.1.2.dist-info/RECORD
