Metadata-Version: 2.4
Name: nonebot-plugin-dice-helper
Version: 0.1.2
Summary: NoneBot 可自定义骰子的骰子插件
Author: Demo
License: MIT
Project-URL: Homepage, https://github.com/CaptainDemo/nonebot-plugin-dice-helper
Project-URL: Repository, https://github.com/CaptainDemo/nonebot-plugin-dice-helper
Requires-Python: >=3.9
License-File: LICENSE
Requires-Dist: nonebot2>=2.4.4
Requires-Dist: nonebot_adapter_onebot>=2.4.6
Requires-Dist: nonebot-plugin-localstore>=0.7.4
Dynamic: license-file
